sqldev-0.0.19.dist-info/METADATA
sqldev-0.0.19.dist-info/WHEEL
sqldev-0.0.19.dist-info/licenses/LICENSE
sqldev/__init__.py
sqldev/_compat.py
sqldev/default.py
sqldev/ext/__init__.py
sqldev/ext/asyncio/__init__.py
sqldev/ext/asyncio/session.py
sqldev/main.py
sqldev/orm/__init__.py
sqldev/orm/session.py
sqldev/pool/__init__.py
sqldev/py.typed
sqldev/sql/__init__.py
sqldev/sql/_expression_select_cls.py
sqldev/sql/_expression_select_gen.py
sqldev/sql/_expression_select_gen.py.jinja2
sqldev/sql/base.py
sqldev/sql/expression.py
sqldev/sql/sqltypes.py
sqldev-0.0.19.dist-info/RECORD
